razdel/__init__.py
razdel/record.py
razdel/rule.py
razdel/split.py
razdel/substring.py
razdel/segmenters/__init__.py
razdel/segmenters/base.py
razdel/segmenters/punct.py
razdel/segmenters/sentenize.py
razdel/segmenters/sokr.py
razdel/segmenters/tokenize.py
razdel/tests/__init__.py
razdel/tests/common.py
razdel/tests/conftest.py
razdel/tests/ctl.py
razdel/tests/gen.py
razdel/tests/partition.py
razdel/tests/test_sentenize.py
razdel/tests/test_tokenize.py
razdel/tests/zoo.py
razdel-0.5.0.dist-info/LICENSE
razdel-0.5.0.dist-info/METADATA
razdel-0.5.0.dist-info/WHEEL
razdel-0.5.0.dist-info/entry_points.txt
razdel-0.5.0.dist-info/top_level.txt
razdel-0.5.0.dist-info/RECORD
