Metadata-Version: 2.1
Name: razdel
Version: 0.5.0
Summary: Splits russian text into tokens, sentences, section. Rule-based
Home-page: https://github.com/natasha/razdel
Author: Alexander Kukushkin
Author-email: alex@alexkuk.ru
License: MIT
Keywords: nlp,natural language processing,russian,token,sentence,tokenize
Platform: UNKNOWN
Classifier: License :: OSI Approved :: MIT License
Classifier: Programming Language :: Python :: 3
